<core:FragmentDefinition xmlns="sap.m" xmlns:l="sap.ui.layout" xmlns:f="sap.ui.layout.form" xmlns:core="sap.ui.core">
	<Dialog id="DeleteDialog" title="Confirmation" titleAlignment="Center" state="Information">
		<f:SimpleForm>
   			<f:content>
   				<Text text="Do you Want Delete the Material" />
   			</f:content>
   		</f:SimpleForm>
		<buttons>
			<Button icon="sap-icon://accept" text="Yes" type="Emphasized" press="onDeletePress"/>
			<Button icon="sap-icon://decline" text="No" press="closeMatDialogbox" type="Ghost"/>
		</buttons>
	</Dialog>
</core:FragmentDefinition>